num_solvers/__init__.py
num_solvers/version.py
num_solvers/__backend/__init__.py
num_solvers/__backend/core_helpers_.py
num_solvers/__backend/errors_.py
num_solvers/__backend/fdm_.py
num_solvers/__backend/interpolation_.py
num_solvers/__backend/iterative_solvers_.py
num_solvers/__backend/matrix_.py
num_solvers/__backend/newton_cotes_.py
num_solvers/__backend/polynomials.py
num_solvers/__backend/root_finding_algorithms_.py
num_solvers/__backend/spline_.py
num_solvers/finite_difference_method/__init__.py
num_solvers/finite_difference_method/fdm.py
num_solvers/integrators/__init__.py
num_solvers/integrators/newton_cotes_integrators.py
num_solvers/interpolators/__init__.py
num_solvers/interpolators/lagrange_interpolation.py
num_solvers/interpolators/newton_interpolation.py
num_solvers/interpolators/spline_interpolation.py
num_solvers/iterative_solvers/__init__.py
num_solvers/iterative_solvers/function_root.py
num_solvers/iterative_solvers/polynomial_root.py
num_solvers/iterative_solvers/odes/__init__.py
num_solvers/iterative_solvers/odes/runge_kutta.py
num_solvers/iterative_solvers/odes/runge_kutta_multi.py
num_solvers/iterative_solvers/system_of_equations/__init__.py
num_solvers/iterative_solvers/system_of_equations/gauss_jacobi.py
num_solvers/iterative_solvers/system_of_equations/gauss_seidel.py
num_solvers/iterative_solvers/system_of_equations/predictor_corrector_methods.py
num_solvers/matrix_decomposition/__init__.py
num_solvers/matrix_decomposition/cholesky_decomposition.py
num_solvers/matrix_decomposition/extra.py
num_solvers/matrix_decomposition/gauss_elimination.py
num_solvers/matrix_decomposition/gauss_methods.py
num_solvers/matrix_decomposition/givens_rotation.py
num_solvers/matrix_decomposition/householder_transformations.py
num_solvers/matrix_decomposition/lu_decomposition.py
num_solvers/matrix_decomposition/qr_decomposition.py
num_solvers/matrix_decomposition/rayleigh_quotient_method.py
num_solvers/matrix_decomposition/steepest_descent.py
num_solvers-0.1.0.dist-info/LICENSE
num_solvers-0.1.0.dist-info/METADATA
num_solvers-0.1.0.dist-info/WHEEL
num_solvers-0.1.0.dist-info/top_level.txt
num_solvers-0.1.0.dist-info/RECORD
