Metadata-Version: 2.1
Name: num_solvers
Version: 0.1.0
Summary: A library for some basic numerical solvers.
Home-page: https://github.com/syedalimohsinbukhari/Solvers
Author: Syed Ali Mohsin Bukhari
Author-email: syedali.b@outlook.com
License: MIT
Classifier: License :: OSI Approved :: MIT License
Classifier: Programming Language :: Python :: 3.9
Classifier: Programming Language :: Python :: 3.10
Classifier: Programming Language :: Python :: 3.11
Requires-Python: >=3.9
License-File: LICENSE
Requires-Dist: numpy ==1.26.4
Requires-Dist: setuptools
Requires-Dist: custom-inherit
Requires-Dist: umatrix
